sqlite_to_erd.py
sqlite_to_erd-0.6.0.dist-info/licenses/LICENSE
sqlite_to_erd-0.6.0.dist-info/METADATA
sqlite_to_erd-0.6.0.dist-info/WHEEL
sqlite_to_erd-0.6.0.dist-info/entry_points.txt
sqlite_to_erd-0.6.0.dist-info/top_level.txt
sqlite_to_erd-0.6.0.dist-info/RECORD
