Metadata-Version: 2.4
Name: sqlite-to-erd
Version: 0.6.0
Summary: Generate ERD diagrams from SQLite databases
Author-email: Stephan Fitzpatrick <knowsuchagency@gmail.com>
License-Expression: MIT
Project-URL: Homepage, https://github.com/knowsuchagency/sqlite-to-erd
Project-URL: Repository, https://github.com/knowsuchagency/sqlite-to-erd.git
Project-URL: Issues, https://github.com/knowsuchagency/sqlite-to-erd/issues
Keywords: sqlite,erd,database,visualization,graphviz,diagram
Classifier: Development Status :: 4 - Beta
Classifier: Intended Audience :: Developers
Classifier: Programming Language :: Python :: 3
Classifier: Programming Language :: Python :: 3.12
Classifier: Programming Language :: Python :: 3.13
Classifier: Topic :: Database
Classifier: Topic :: Software Development :: Libraries :: Python Modules
Classifier: Topic :: Utilities
Requires-Python: >=3.12
License-File: LICENSE
Requires-Dist: click>=8.2.1
Dynamic: license-file
